metaman/__init__.py
metaman/_core.py
metaman/_deprecate.py
metaman/py.typed
bolton_metaman-0.1.2.dist-info/METADATA
bolton_metaman-0.1.2.dist-info/WHEEL
bolton_metaman-0.1.2.dist-info/top_level.txt
bolton_metaman-0.1.2.dist-info/RECORD
