Metadata-Version: 2.1
Name: bolton-metaman
Version: 0.1.2
Summary: metadata manager (METAMAN)... Makes use of Python's dynamic nature to inspect a program's internals.
Home-page: https://github.com/python-boltons/metaman
Author: Bryan M Bugyi
Author-email: bryanbugyi34@gmail.com
License: MIT license
Classifier: Development Status :: 3 - Alpha
Classifier: Intended Audience :: Developers
Classifier: License :: OSI Approved :: MIT License
Classifier: Natural Language :: English
Classifier: Programming Language :: Python :: 3
Classifier: Programming Language :: Python :: 3.8
Classifier: Programming Language :: Python :: 3.9
Classifier: Programming Language :: Python :: 3.10
Requires-Python: >=3.8
